howler_client/__init__.py
howler_client/client.py
howler_client/common/__init__.py
howler_client/common/dict_utils.py
howler_client/common/utils.py
howler_client/connection.py
howler_client/logger.py
howler_client/module/__init__.py
howler_client/module/bundle.py
howler_client/module/comment.py
howler_client/module/help.py
howler_client/module/hit.py
howler_client/module/search/__init__.py
howler_client/module/search/chunk.py
howler_client/module/search/facet.py
howler_client/module/search/fields.py
howler_client/module/search/grouped.py
howler_client/module/search/histogram.py
howler_client/module/search/stats.py
howler_client/module/search/stream.py
howler_client/module/user.py
howler_client/utils/__init__.py
howler_client/utils/json_encoders.py
howler_client-2.4.0.dist-info/LICENSE
howler_client-2.4.0.dist-info/METADATA
howler_client-2.4.0.dist-info/WHEEL
howler_client-2.4.0.dist-info/entry_points.txt
howler_client-2.4.0.dist-info/RECORD
